.gitignore
MANIFEST.in
README.txt
setup.cfg
setup.py
collective/__init__.py
collective.slickslideshow.egg-info/PKG-INFO
collective.slickslideshow.egg-info/SOURCES.txt
collective.slickslideshow.egg-info/dependency_links.txt
collective.slickslideshow.egg-info/entry_points.txt
collective.slickslideshow.egg-info/namespace_packages.txt
collective.slickslideshow.egg-info/not-zip-safe
collective.slickslideshow.egg-info/paster_plugins.txt
collective.slickslideshow.egg-info/requires.txt
collective.slickslideshow.egg-info/top_level.txt
collective/slickslideshow/__init__.py
collective/slickslideshow/adapters.py
collective/slickslideshow/configure.zcml
collective/slickslideshow/events.py
collective/slickslideshow/indexers.py
collective/slickslideshow/interfaces.py
collective/slickslideshow/setuphandlers.py
collective/slickslideshow/tests.py
collective/slickslideshow/browser/__init__.py
collective/slickslideshow/browser/configure.zcml
collective/slickslideshow/browser/views.py
collective/slickslideshow/browser/css/vendor/ajax-loader.gif
collective/slickslideshow/browser/css/vendor/slick.css
collective/slickslideshow/browser/css/vendor/fonts/slick.eot
collective/slickslideshow/browser/css/vendor/fonts/slick.svg
collective/slickslideshow/browser/css/vendor/fonts/slick.ttf
collective/slickslideshow/browser/css/vendor/fonts/slick.woff
collective/slickslideshow/browser/js/slickslideshow.js
collective/slickslideshow/browser/js/vendor/.DS_Store
collective/slickslideshow/browser/js/vendor/slick.js
collective/slickslideshow/profiles/default/browserlayer.xml
collective/slickslideshow/profiles/default/collective_slickslideshow-default.txt
collective/slickslideshow/profiles/default/cssregistry.xml
collective/slickslideshow/profiles/default/jsregistry.xml
collective/slickslideshow/profiles/default/metadata.xml
collective/slickslideshow/profiles/default/types/Products.mediaObject.object.xml
docs/HISTORY.txt
docs/INSTALL.txt
docs/LICENSE.GPL
docs/LICENSE.txt