Metadata-Version: 1.1
Name: collective.slickslideshow
Version: 0.0.5
Summary: Slick Slideshow solution for Plone.
Home-page: https://github.com/intk/collective.slickslideshow
Author: Andre Goncalves
Author-email: andre@intk.com
License: GPL
Download-URL: https://github.com/intk/collective.slickslideshow/tarball/0.0.1
Keywords: slideshow
Platform: UNKNOWN
Classifier: Framework :: Plone
Classifier: Programming Language :: Python
